ulangel/__init__.py
ulangel/__pycache__/__init__.cpython-38.pyc
ulangel/data/data_packer.py
ulangel/data/text_processor.py
ulangel/data/__pycache__/data_packer.cpython-38.pyc
ulangel/data/__pycache__/text_processor.cpython-38.pyc
ulangel/rnn/dropouts.py
ulangel/rnn/nn_block.py
ulangel/rnn/__pycache__/dropouts.cpython-38.pyc
ulangel/rnn/__pycache__/nn_block.cpython-38.pyc
ulangel/utils/callbacks.py
ulangel/utils/learner.py
ulangel/utils/optimizer.py
ulangel/utils/stats.py
ulangel/utils/__pycache__/callbacks.cpython-38.pyc
ulangel/utils/__pycache__/learner.cpython-38.pyc
ulangel/utils/__pycache__/optimizer.cpython-38.pyc
ulangel/utils/__pycache__/stats.cpython-38.pyc
ulangel-0.1.1.dist-info/LICENSE
ulangel-0.1.1.dist-info/METADATA
ulangel-0.1.1.dist-info/WHEEL
ulangel-0.1.1.dist-info/top_level.txt
ulangel-0.1.1.dist-info/RECORD
