Metadata-Version: 2.1
Name: ulangel
Version: 0.1.1
Summary: All-in-one framework for NLP Transfer Learning Classification
Home-page: https://github.com/uchange/ulangel
Author: Célia Guanguan ZHANG
Author-email: guanguan@uchange.co
License: UNKNOWN
Platform: UNKNOWN
Classifier: Development Status :: 3 - Alpha
Classifier: Environment :: Console
Classifier: Intended Audience :: Developers
Classifier: License :: OSI Approved :: Apache Software License
Classifier: Operating System :: OS Independent
Classifier: Topic :: Software Development :: Libraries :: Python Modules
Classifier: Programming Language :: Python
Classifier: Programming Language :: Python :: 3.6
Classifier: Topic :: Utilities
Requires-Dist: torch (==1.4.0)
Requires-Dist: torchvision (==0.5.0)
Requires-Dist: numpy (==1.18.1)
Requires-Dist: emoji (==0.5.4)
